aikosmo_register_service/__init__.py
aikosmo_register_service/register.py
aikosmo_register_service-0.1.dist-info/METADATA
aikosmo_register_service-0.1.dist-info/WHEEL
aikosmo_register_service-0.1.dist-info/top_level.txt
aikosmo_register_service-0.1.dist-info/RECORD
